zenopy/__init__.py
zenopy/_version.py
zenopy/client.py
zenopy/deposition_actions.py
zenopy/deposition_files.py
zenopy/depositions.py
zenopy/errors.py
zenopy/metadata.py
zenopy/record.py
zenopy/records.py
zenopy/resources.py
zenopy/test_client.ipynb
zenopy/test_deposition_actions.ipynb
zenopy/test_deposition_files.ipynb
zenopy/test_depositions.ipynb
zenopy/test_entity.ipynb
zenopy/test_records.ipynb
zenopy/test_token.ipynb
zenopy/utils.py
zenopy/tests/__init__.py
zenopy/tests/test_zenopy.py
zenopy-2022.10.29.dist-info/AUTHORS.rst
zenopy-2022.10.29.dist-info/LICENSE
zenopy-2022.10.29.dist-info/METADATA
zenopy-2022.10.29.dist-info/WHEEL
zenopy-2022.10.29.dist-info/top_level.txt
zenopy-2022.10.29.dist-info/RECORD
