Metadata-Version: 2.1
Name: zenopy
Version: 2022.10.29
Summary: zenopy: A Python wrapper package for Zenodo API
Home-page: https://github.com/MolSSI/zenopy
Author: Mohammad Mostafanejad
Author-email: smostafanejad@vt.edu
License: GNU Lesser General Public License v3
Keywords: zenopy
Classifier: Development Status :: 2 - Pre-Alpha
Classifier: Intended Audience :: Developers
Classifier: License :: OSI Approved :: GNU Lesser General Public License v3 or later (LGPLv3+)
Classifier: Natural Language :: English
Classifier: Programming Language :: Python :: 3 :: Only
Classifier: Programming Language :: Python :: 3.10
License-File: LICENSE
License-File: AUTHORS.rst
Requires-Dist: requests
Requires-Dist: validators
Requires-Dist: renku-sphinx-theme
Provides-Extra: docs
Requires-Dist: sphinx (==1.2.3) ; extra == 'docs'
Requires-Dist: sphinxcontrib-napoleon ; extra == 'docs'
Requires-Dist: sphinx-rtd-theme ; extra == 'docs'
Requires-Dist: renku-sphinx-theme ; extra == 'docs'
Requires-Dist: numpydoc ; extra == 'docs'
Provides-Extra: lint
Requires-Dist: black ; extra == 'lint'
Provides-Extra: tests
Requires-Dist: pytest ; extra == 'tests'
Requires-Dist: pytest-cov ; extra == 'tests'
